[
  {
    "brand": "Nordeco",
    "name": "Адриатика",
    "file": "Nordeco 2024/Адриатика.jpg",
    "url": "https://raw.githubusercontent.com/mebelshare/spacemebel-decors/main/Nordeco 2024/Адриатика.jpg"
  },
  {
    "brand": "Nordeco",
    "name": "Беж Камео",
    "file": "Nordeco 2024/Беж Камео.jpg",
    "url": "https://raw.githubusercontent.com/mebelshare/spacemebel-decors/main/Nordeco 2024/Беж Камео.jpg"
  },
  {
    "brand": "Nordeco",
    "name": "Бежевый",
    "file": "Nordeco 2024/Бежевый.jpg",
    "url": "https://raw.githubusercontent.com/mebelshare/spacemebel-decors/main/Nordeco 2024/Бежевый.jpg"
  },
  {
    "brand": "Nordeco",
    "name": "Белый",
    "file": "Nordeco 2024/Белый.jpg",
    "url": "https://raw.githubusercontent.com/mebelshare/spacemebel-decors/main/Nordeco 2024/Белый.jpg"
  },
  {
    "brand": "Nordeco",
    "name": "Белый Жемчуг",
    "file": "Nordeco 2024/Белый Жемчуг.jpg",
    "url": "https://raw.githubusercontent.com/mebelshare/spacemebel-decors/main/Nordeco 2024/Белый Жемчуг.jpg"
  },
  {
    "brand": "Nordeco",
    "name": "Белый Лотос",
    "file": "Nordeco 2024/Белый Лотос.jpg",
    "url": "https://raw.githubusercontent.com/mebelshare/spacemebel-decors/main/Nordeco 2024/Белый Лотос.jpg"
  },
  {
    "brand": "Nordeco",
    "name": "Бетон Пайн",
    "file": "Nordeco 2024/Бетон Пайн.jpg",
    "url": "https://raw.githubusercontent.com/mebelshare/spacemebel-decors/main/Nordeco 2024/Бетон Пайн.jpg"
  },
  {
    "brand": "Nordeco",
    "name": "Бетона Пайн светлый",
    "file": "Nordeco 2024/Бетона Пайн светлый.jpg",
    "url": "https://raw.githubusercontent.com/mebelshare/spacemebel-decors/main/Nordeco 2024/Бетона Пайн светлый.jpg"
  },
  {
    "brand": "Nordeco",
    "name": "Бодега Белый",
    "file": "Nordeco 2024/Бодега Белый.jpg",
    "url": "https://raw.githubusercontent.com/mebelshare/spacemebel-decors/main/Nordeco 2024/Бодега Белый.jpg"
  },
  {
    "brand": "Nordeco",
    "name": "Бук Бавария светлый",
    "file": "Nordeco 2024/Бук Бавария светлый.jpg",
    "url": "https://raw.githubusercontent.com/mebelshare/spacemebel-decors/main/Nordeco 2024/Бук Бавария светлый.jpg"
  },
  {
    "brand": "Nordeco",
    "name": "Бунратти",
    "file": "Nordeco 2024/Бунратти.jpg",
    "url": "https://raw.githubusercontent.com/mebelshare/spacemebel-decors/main/Nordeco 2024/Бунратти.jpg"
  },
  {
    "brand": "Nordeco",
    "name": "Венге Аруба",
    "file": "Nordeco 2024/Венге Аруба.jpg",
    "url": "https://raw.githubusercontent.com/mebelshare/spacemebel-decors/main/Nordeco 2024/Венге Аруба.jpg"
  },
  {
    "brand": "Nordeco",
    "name": "Венге Линум",
    "file": "Nordeco 2024/Венге Линум.jpg",
    "url": "https://raw.githubusercontent.com/mebelshare/spacemebel-decors/main/Nordeco 2024/Венге Линум.jpg"
  },
  {
    "brand": "Nordeco",
    "name": "Венге Цаво",
    "file": "Nordeco 2024/Венге Цаво.jpg",
    "url": "https://raw.githubusercontent.com/mebelshare/spacemebel-decors/main/Nordeco 2024/Венге Цаво.jpg"
  },
  {
    "brand": "Nordeco",
    "name": "Венис",
    "file": "Nordeco 2024/Венис.jpg",
    "url": "https://raw.githubusercontent.com/mebelshare/spacemebel-decors/main/Nordeco 2024/Венис.jpg"
  },
  {
    "brand": "Nordeco",
    "name": "Винтерберг",
    "file": "Nordeco 2024/Винтерберг.jpg",
    "url": "https://raw.githubusercontent.com/mebelshare/spacemebel-decors/main/Nordeco 2024/Винтерберг.jpg"
  },
  {
    "brand": "Nordeco",
    "name": "Вяз Швейцарский светлый",
    "file": "Nordeco 2024/Вяз Швейцарский светлый.jpg",
    "url": "https://raw.githubusercontent.com/mebelshare/spacemebel-decors/main/Nordeco 2024/Вяз Швейцарский светлый.jpg"
  },
  {
    "brand": "Nordeco",
    "name": "Графит",
    "file": "Nordeco 2024/Графит.jpg",
    "url": "https://raw.githubusercontent.com/mebelshare/spacemebel-decors/main/Nordeco 2024/Графит.jpg"
  },
  {
    "brand": "Nordeco",
    "name": "Греви",
    "file": "Nordeco 2024/Греви.jpg",
    "url": "https://raw.githubusercontent.com/mebelshare/spacemebel-decors/main/Nordeco 2024/Греви.jpg"
  },
  {
    "brand": "Nordeco",
    "name": "Грейдж",
    "file": "Nordeco 2024/Грейдж.jpg",
    "url": "https://raw.githubusercontent.com/mebelshare/spacemebel-decors/main/Nordeco 2024/Грейдж.jpg"
  },
  {
    "brand": "Nordeco",
    "name": "Дуб Апрельский Нордик",
    "file": "Nordeco 2024/Дуб Апрельский Нордик.jpg",
    "url": "https://raw.githubusercontent.com/mebelshare/spacemebel-decors/main/Nordeco 2024/Дуб Апрельский Нордик.jpg"
  },
  {
    "brand": "Nordeco",
    "name": "Дуб Апрельский Шоколадный",
    "file": "Nordeco 2024/Дуб Апрельский Шоколадный.jpg",
    "url": "https://raw.githubusercontent.com/mebelshare/spacemebel-decors/main/Nordeco 2024/Дуб Апрельский Шоколадный.jpg"
  },
  {
    "brand": "Nordeco",
    "name": "Дуб Аризона",
    "file": "Nordeco 2024/Дуб Аризона.jpg",
    "url": "https://raw.githubusercontent.com/mebelshare/spacemebel-decors/main/Nordeco 2024/Дуб Аризона.jpg"
  },
  {
    "brand": "Nordeco",
    "name": "Дуб Атланта",
    "file": "Nordeco 2024/Дуб Атланта.jpg",
    "url": "https://raw.githubusercontent.com/mebelshare/spacemebel-decors/main/Nordeco 2024/Дуб Атланта.jpg"
  },
  {
    "brand": "Nordeco",
    "name": "Дуб Вотан",
    "file": "Nordeco 2024/Дуб Вотан.jpg",
    "url": "https://raw.githubusercontent.com/mebelshare/spacemebel-decors/main/Nordeco 2024/Дуб Вотан.jpg"
  },
  {
    "brand": "Nordeco",
    "name": "Дуб Гарден светлый",
    "file": "Nordeco 2024/Дуб Гарден светлый.jpg",
    "url": "https://raw.githubusercontent.com/mebelshare/spacemebel-decors/main/Nordeco 2024/Дуб Гарден светлый.jpg"
  },
  {
    "brand": "Nordeco",
    "name": "Дуб Гарден тёмный",
    "file": "Nordeco 2024/Дуб Гарден тёмный.jpg",
    "url": "https://raw.githubusercontent.com/mebelshare/spacemebel-decors/main/Nordeco 2024/Дуб Гарден тёмный.jpg"
  },
  {
    "brand": "Nordeco",
    "name": "Дуб Делано",
    "file": "Nordeco 2024/Дуб Делано.jpg",
    "url": "https://raw.githubusercontent.com/mebelshare/spacemebel-decors/main/Nordeco 2024/Дуб Делано.jpg"
  },
  {
    "brand": "Nordeco",
    "name": "Дуб Делано натуральный",
    "file": "Nordeco 2024/Дуб Делано натуральный.jpg",
    "url": "https://raw.githubusercontent.com/mebelshare/spacemebel-decors/main/Nordeco 2024/Дуб Делано натуральный.jpg"
  },
  {
    "brand": "Nordeco",
    "name": "Дуб Катания",
    "file": "Nordeco 2024/Дуб Катания.jpg",
    "url": "https://raw.githubusercontent.com/mebelshare/spacemebel-decors/main/Nordeco 2024/Дуб Катания.jpg"
  },
  {
    "brand": "Nordeco",
    "name": "Дуб Маувелла",
    "file": "Nordeco 2024/Дуб Маувелла.jpg",
    "url": "https://raw.githubusercontent.com/mebelshare/spacemebel-decors/main/Nordeco 2024/Дуб Маувелла.jpg"
  },
  {
    "brand": "Nordeco",
    "name": "Дуб Омега светлый",
    "file": "Nordeco 2024/Дуб Омега светлый.jpg",
    "url": "https://raw.githubusercontent.com/mebelshare/spacemebel-decors/main/Nordeco 2024/Дуб Омега светлый.jpg"
  },
  {
    "brand": "Nordeco",
    "name": "Дуб Патинато",
    "file": "Nordeco 2024/Дуб Патинато.jpg",
    "url": "https://raw.githubusercontent.com/mebelshare/spacemebel-decors/main/Nordeco 2024/Дуб Патинато.jpg"
  },
  {
    "brand": "Nordeco",
    "name": "Дуб Самдал",
    "file": "Nordeco 2024/Дуб Самдал.jpg",
    "url": "https://raw.githubusercontent.com/mebelshare/spacemebel-decors/main/Nordeco 2024/Дуб Самдал.jpg"
  },
  {
    "brand": "Nordeco",
    "name": "Дуб Сонома 001",
    "file": "Nordeco 2024/Дуб Сонома 001.jpg",
    "url": "https://raw.githubusercontent.com/mebelshare/spacemebel-decors/main/Nordeco 2024/Дуб Сонома 001.jpg"
  },
  {
    "brand": "Nordeco",
    "name": "Дуб Тоскана дымчатый",
    "file": "Nordeco 2024/Дуб Тоскана дымчатый.jpg",
    "url": "https://raw.githubusercontent.com/mebelshare/spacemebel-decors/main/Nordeco 2024/Дуб Тоскана дымчатый.jpg"
  },
  {
    "brand": "Nordeco",
    "name": "Дуб Харбор Белый",
    "file": "Nordeco 2024/Дуб Харбор Белый.jpg",
    "url": "https://raw.githubusercontent.com/mebelshare/spacemebel-decors/main/Nordeco 2024/Дуб Харбор Белый.jpg"
  },
  {
    "brand": "Nordeco",
    "name": "Дуб Чанкли",
    "file": "Nordeco 2024/Дуб Чанкли.jpg",
    "url": "https://raw.githubusercontent.com/mebelshare/spacemebel-decors/main/Nordeco 2024/Дуб Чанкли.jpg"
  },
  {
    "brand": "Nordeco",
    "name": "Дуб Честерфилд 003",
    "file": "Nordeco 2024/Дуб Честерфилд 003.jpg",
    "url": "https://raw.githubusercontent.com/mebelshare/spacemebel-decors/main/Nordeco 2024/Дуб Честерфилд 003.jpg"
  },
  {
    "brand": "Nordeco",
    "name": "Дуб Шамони светлый",
    "file": "Nordeco 2024/Дуб Шамони светлый.jpg",
    "url": "https://raw.githubusercontent.com/mebelshare/spacemebel-decors/main/Nordeco 2024/Дуб Шамони светлый.jpg"
  },
  {
    "brand": "Nordeco",
    "name": "Дуб Шамони темный",
    "file": "Nordeco 2024/Дуб Шамони темный.jpg",
    "url": "https://raw.githubusercontent.com/mebelshare/spacemebel-decors/main/Nordeco 2024/Дуб Шамони темный.jpg"
  },
  {
    "brand": "Nordeco",
    "name": "Дымчатый зеленый",
    "file": "Nordeco 2024/Дымчатый зеленый.jpg",
    "url": "https://raw.githubusercontent.com/mebelshare/spacemebel-decors/main/Nordeco 2024/Дымчатый зеленый.jpg"
  },
  {
    "brand": "Nordeco",
    "name": "Дымчатый серый",
    "file": "Nordeco 2024/Дымчатый серый.jpg",
    "url": "https://raw.githubusercontent.com/mebelshare/spacemebel-decors/main/Nordeco 2024/Дымчатый серый.jpg"
  },
  {
    "brand": "Nordeco",
    "name": "Зейдан",
    "file": "Nordeco 2024/Зейдан.jpg",
    "url": "https://raw.githubusercontent.com/mebelshare/spacemebel-decors/main/Nordeco 2024/Зейдан.jpg"
  },
  {
    "brand": "Nordeco",
    "name": "Капучино",
    "file": "Nordeco 2024/Капучино.jpg",
    "url": "https://raw.githubusercontent.com/mebelshare/spacemebel-decors/main/Nordeco 2024/Капучино.jpg"
  },
  {
    "brand": "Nordeco",
    "name": "Кашемир",
    "file": "Nordeco 2024/Кашемир.jpg",
    "url": "https://raw.githubusercontent.com/mebelshare/spacemebel-decors/main/Nordeco 2024/Кашемир.jpg"
  },
  {
    "brand": "Nordeco",
    "name": "Кронберг",
    "file": "Nordeco 2024/Кронберг.jpg",
    "url": "https://raw.githubusercontent.com/mebelshare/spacemebel-decors/main/Nordeco 2024/Кронберг.jpg"
  },
  {
    "brand": "Nordeco",
    "name": "Лево",
    "file": "Nordeco 2024/Лево.jpg",
    "url": "https://raw.githubusercontent.com/mebelshare/spacemebel-decors/main/Nordeco 2024/Лево.jpg"
  },
  {
    "brand": "Nordeco",
    "name": "Линия темная",
    "file": "Nordeco 2024/Линия темная.jpg",
    "url": "https://raw.githubusercontent.com/mebelshare/spacemebel-decors/main/Nordeco 2024/Линия темная.jpg"
  },
  {
    "brand": "Nordeco",
    "name": "Метрополитан",
    "file": "Nordeco 2024/Метрополитан.jpg",
    "url": "https://raw.githubusercontent.com/mebelshare/spacemebel-decors/main/Nordeco 2024/Метрополитан.jpg"
  },
  {
    "brand": "Nordeco",
    "name": "Оникс",
    "file": "Nordeco 2024/Оникс.jpg",
    "url": "https://raw.githubusercontent.com/mebelshare/spacemebel-decors/main/Nordeco 2024/Оникс.jpg"
  },
  {
    "brand": "Nordeco",
    "name": "Пасифай",
    "file": "Nordeco 2024/Пасифай.jpg",
    "url": "https://raw.githubusercontent.com/mebelshare/spacemebel-decors/main/Nordeco 2024/Пасифай.jpg"
  },
  {
    "brand": "Nordeco",
    "name": "Пихта серебристая",
    "file": "Nordeco 2024/Пихта серебристая.jpg",
    "url": "https://raw.githubusercontent.com/mebelshare/spacemebel-decors/main/Nordeco 2024/Пихта серебристая.jpg"
  },
  {
    "brand": "Nordeco",
    "name": "Платина",
    "file": "Nordeco 2024/Платина.jpg",
    "url": "https://raw.githubusercontent.com/mebelshare/spacemebel-decors/main/Nordeco 2024/Платина.jpg"
  },
  {
    "brand": "Nordeco",
    "name": "Пыльный розовый",
    "file": "Nordeco 2024/Пыльный розовый.jpg",
    "url": "https://raw.githubusercontent.com/mebelshare/spacemebel-decors/main/Nordeco 2024/Пыльный розовый.jpg"
  },
  {
    "brand": "Nordeco",
    "name": "Светло-серый",
    "file": "Nordeco 2024/Светло-серый.jpg",
    "url": "https://raw.githubusercontent.com/mebelshare/spacemebel-decors/main/Nordeco 2024/Светло-серый.jpg"
  },
  {
    "brand": "Nordeco",
    "name": "Серый камень",
    "file": "Nordeco 2024/Серый камень.jpg",
    "url": "https://raw.githubusercontent.com/mebelshare/spacemebel-decors/main/Nordeco 2024/Серый камень.jpg"
  },
  {
    "brand": "Nordeco",
    "name": "Серый темный",
    "file": "Nordeco 2024/Серый темный.jpg",
    "url": "https://raw.githubusercontent.com/mebelshare/spacemebel-decors/main/Nordeco 2024/Серый темный.jpg"
  },
  {
    "brand": "Nordeco",
    "name": "Сливочный",
    "file": "Nordeco 2024/Сливочный.jpg",
    "url": "https://raw.githubusercontent.com/mebelshare/spacemebel-decors/main/Nordeco 2024/Сливочный.jpg"
  },
  {
    "brand": "Nordeco",
    "name": "Сосна Скандинавия",
    "file": "Nordeco 2024/Сосна Скандинавия.jpg",
    "url": "https://raw.githubusercontent.com/mebelshare/spacemebel-decors/main/Nordeco 2024/Сосна Скандинавия.jpg"
  },
  {
    "brand": "Nordeco",
    "name": "Супер белый",
    "file": "Nordeco 2024/Супер белый.jpg",
    "url": "https://raw.githubusercontent.com/mebelshare/spacemebel-decors/main/Nordeco 2024/Супер белый.jpg"
  },
  {
    "brand": "Nordeco",
    "name": "Сэнд",
    "file": "Nordeco 2024/Сэнд.jpg",
    "url": "https://raw.githubusercontent.com/mebelshare/spacemebel-decors/main/Nordeco 2024/Сэнд.jpg"
  },
  {
    "brand": "Nordeco",
    "name": "Таксония Медовая",
    "file": "Nordeco 2024/Таксония Медовая.jpg",
    "url": "https://raw.githubusercontent.com/mebelshare/spacemebel-decors/main/Nordeco 2024/Таксония Медовая.jpg"
  },
  {
    "brand": "Nordeco",
    "name": "Таксония Шоколадная",
    "file": "Nordeco 2024/Таксония Шоколадная.jpg",
    "url": "https://raw.githubusercontent.com/mebelshare/spacemebel-decors/main/Nordeco 2024/Таксония Шоколадная.jpg"
  },
  {
    "brand": "Nordeco",
    "name": "Тауп",
    "file": "Nordeco 2024/Тауп.jpg",
    "url": "https://raw.githubusercontent.com/mebelshare/spacemebel-decors/main/Nordeco 2024/Тауп.jpg"
  },
  {
    "brand": "Nordeco",
    "name": "Титан",
    "file": "Nordeco 2024/Титан.jpg",
    "url": "https://raw.githubusercontent.com/mebelshare/spacemebel-decors/main/Nordeco 2024/Титан.jpg"
  },
  {
    "brand": "Nordeco",
    "name": "Уни неро",
    "file": "Nordeco 2024/Уни неро.jpg",
    "url": "https://raw.githubusercontent.com/mebelshare/spacemebel-decors/main/Nordeco 2024/Уни неро.jpg"
  },
  {
    "brand": "Nordeco",
    "name": "Файерстоун",
    "file": "Nordeco 2024/Файерстоун.jpg",
    "url": "https://raw.githubusercontent.com/mebelshare/spacemebel-decors/main/Nordeco 2024/Файерстоун.jpg"
  },
  {
    "brand": "Nordeco",
    "name": "Финдус бежевый",
    "file": "Nordeco 2024/Финдус бежевый.jpg",
    "url": "https://raw.githubusercontent.com/mebelshare/spacemebel-decors/main/Nordeco 2024/Финдус бежевый.jpg"
  },
  {
    "brand": "Nordeco",
    "name": "Цемент светлый",
    "file": "Nordeco 2024/Цемент светлый.jpg",
    "url": "https://raw.githubusercontent.com/mebelshare/spacemebel-decors/main/Nordeco 2024/Цемент светлый.jpg"
  },
  {
    "brand": "Nordeco",
    "name": "Цемент Темный",
    "file": "Nordeco 2024/Цемент Темный.jpg",
    "url": "https://raw.githubusercontent.com/mebelshare/spacemebel-decors/main/Nordeco 2024/Цемент Темный.jpg"
  },
  {
    "brand": "Nordeco",
    "name": "Юстус",
    "file": "Nordeco 2024/Юстус.jpg",
    "url": "https://raw.githubusercontent.com/mebelshare/spacemebel-decors/main/Nordeco 2024/Юстус.jpg"
  },
  {
    "brand": "Nordeco",
    "name": "Ясень Анкор белый",
    "file": "Nordeco 2024/Ясень Анкор белый.jpg",
    "url": "https://raw.githubusercontent.com/mebelshare/spacemebel-decors/main/Nordeco 2024/Ясень Анкор белый.jpg"
  },
  {
    "brand": "Nordeco",
    "name": "Ясень Анкор светлый",
    "file": "Nordeco 2024/Ясень Анкор светлый.jpg",
    "url": "https://raw.githubusercontent.com/mebelshare/spacemebel-decors/main/Nordeco 2024/Ясень Анкор светлый.jpg"
  },
  {
    "brand": "Nordeco",
    "name": "Ясень Анкор темный",
    "file": "Nordeco 2024/Ясень Анкор темный.jpg",
    "url": "https://raw.githubusercontent.com/mebelshare/spacemebel-decors/main/Nordeco 2024/Ясень Анкор темный.jpg"
  },
  {
    "brand": "Nordeco",
    "name": "Ясень Ориноко",
    "file": "Nordeco 2024/Ясень Ориноко.jpg",
    "url": "https://raw.githubusercontent.com/mebelshare/spacemebel-decors/main/Nordeco 2024/Ясень Ориноко.jpg"
  },
  {
    "brand": "Nordeco",
    "name": "Ясмунд",
    "file": "Nordeco 2024/Ясмунд.jpg",
    "url": "https://raw.githubusercontent.com/mebelshare/spacemebel-decors/main/Nordeco 2024/Ясмунд.jpg"
  }
  {
    "brand": "Slotex",
    "name": "0091_a_venice_600x1300",
    "file": "Slotex/0091_a_venice_600x1300.jpg",
    "url": "https://raw.githubusercontent.com/mebelshare/spacemebel-decors/main/Slotex/0091_a_venice_600x1300.jpg"
  },
  {
    "brand": "Slotex",
    "name": "0093_a_sezamo_600x1300",
    "file": "Slotex/0093_a_sezamo_600x1300.jpg",
    "url": "https://raw.githubusercontent.com/mebelshare/spacemebel-decors/main/Slotex/0093_a_sezamo_600x1300.jpg"
  },
  {
    "brand": "Slotex",
    "name": "1021_1_chernyj_600x1300",
    "file": "Slotex/1021_1_chernyj_600x1300.jpg",
    "url": "https://raw.githubusercontent.com/mebelshare/spacemebel-decors/main/Slotex/1021_1_chernyj_600x1300.jpg"
  },
  {
    "brand": "Slotex",
    "name": "1021_q_chernyj_600x1300",
    "file": "Slotex/1021_q_chernyj_600x1300.jpg",
    "url": "https://raw.githubusercontent.com/mebelshare/spacemebel-decors/main/Slotex/1021_q_chernyj_600x1300.jpg"
  },
  {
    "brand": "Slotex",
    "name": "1100_1_belyj-ledyanoj_600x1300",
    "file": "Slotex/1100_1_belyj-ledyanoj_600x1300.jpg",
    "url": "https://raw.githubusercontent.com/mebelshare/spacemebel-decors/main/Slotex/1100_1_belyj-ledyanoj_600x1300.jpg"
  },
  {
    "brand": "Slotex",
    "name": "2013_so_yurskij-kamen_600x1300",
    "file": "Slotex/2013_so_yurskij-kamen_600x1300.jpg",
    "url": "https://raw.githubusercontent.com/mebelshare/spacemebel-decors/main/Slotex/2013_so_yurskij-kamen_600x1300.jpg"
  },
  {
    "brand": "Slotex",
    "name": "2047_sc_madeira-light_600x1300",
    "file": "Slotex/2047_sc_madeira-light_600x1300.jpg",
    "url": "https://raw.githubusercontent.com/mebelshare/spacemebel-decors/main/Slotex/2047_sc_madeira-light_600x1300.jpg"
  },
  {
    "brand": "Slotex",
    "name": "2048_sc_madeira-dark_600x1300",
    "file": "Slotex/2048_sc_madeira-dark_600x1300.jpg",
    "url": "https://raw.githubusercontent.com/mebelshare/spacemebel-decors/main/Slotex/2048_sc_madeira-dark_600x1300.jpg"
  },
  {
    "brand": "Slotex",
    "name": "2235_s_semolina-seraya_600x1300",
    "file": "Slotex/2235_s_semolina-seraya_600x1300.jpg",
    "url": "https://raw.githubusercontent.com/mebelshare/spacemebel-decors/main/Slotex/2235_s_semolina-seraya_600x1300.jpg"
  },
  {
    "brand": "Slotex",
    "name": "2236_1_semolina-bezhevaya_600x1300",
    "file": "Slotex/2236_1_semolina-bezhevaya_600x1300.jpg",
    "url": "https://raw.githubusercontent.com/mebelshare/spacemebel-decors/main/Slotex/2236_1_semolina-bezhevaya_600x1300.jpg"
  },
  {
    "brand": "Slotex",
    "name": "2237_6_semolina-karamelnaya_600h1300",
    "file": "Slotex/2237_6_semolina-karamelnaya_600h1300.jpg",
    "url": "https://raw.githubusercontent.com/mebelshare/spacemebel-decors/main/Slotex/2237_6_semolina-karamelnaya_600h1300.jpg"
  },
  {
    "brand": "Slotex",
    "name": "2323_bst_etna_600x1300",
    "file": "Slotex/2323_bst_etna_600x1300.jpg",
    "url": "https://raw.githubusercontent.com/mebelshare/spacemebel-decors/main/Slotex/2323_bst_etna_600x1300.jpg"
  },
  {
    "brand": "Slotex",
    "name": "2324_bst_pattajya_600x1300",
    "file": "Slotex/2324_bst_pattajya_600x1300.jpg",
    "url": "https://raw.githubusercontent.com/mebelshare/spacemebel-decors/main/Slotex/2324_bst_pattajya_600x1300.jpg"
  },
  {
    "brand": "Slotex",
    "name": "2326_r_vintazh_600x1300",
    "file": "Slotex/2326_r_vintazh_600x1300.jpg",
    "url": "https://raw.githubusercontent.com/mebelshare/spacemebel-decors/main/Slotex/2326_r_vintazh_600x1300.jpg"
  },
  {
    "brand": "Slotex",
    "name": "2327_so_iolanta_600x1300",
    "file": "Slotex/2327_so_iolanta_600x1300.jpg",
    "url": "https://raw.githubusercontent.com/mebelshare/spacemebel-decors/main/Slotex/2327_so_iolanta_600x1300.jpg"
  },
  {
    "brand": "Slotex",
    "name": "2328_travertin-katalonskij_600x1300",
    "file": "Slotex/2328_travertin-katalonskij_600x1300.jpg",
    "url": "https://raw.githubusercontent.com/mebelshare/spacemebel-decors/main/Slotex/2328_travertin-katalonskij_600x1300.jpg"
  },
  {
    "brand": "Slotex",
    "name": "2329_so_la-skala_600x1300",
    "file": "Slotex/2329_so_la-skala_600x1300.jpg",
    "url": "https://raw.githubusercontent.com/mebelshare/spacemebel-decors/main/Slotex/2329_so_la-skala_600x1300.jpg"
  },
  {
    "brand": "Slotex",
    "name": "2333_q_balkanskij-slanets-chernyj-_600x1300",
    "file": "Slotex/2333_q_balkanskij-slanets-chernyj-_600x1300.jpg",
    "url": "https://raw.githubusercontent.com/mebelshare/spacemebel-decors/main/Slotex/2333_q_balkanskij-slanets-chernyj-_600x1300.jpg"
  },
  {
    "brand": "Slotex",
    "name": "2337_1_mramor-bezhevyj_600x1300",
    "file": "Slotex/2337_1_mramor-bezhevyj_600x1300.jpg",
    "url": "https://raw.githubusercontent.com/mebelshare/spacemebel-decors/main/Slotex/2337_1_mramor-bezhevyj_600x1300.jpg"
  },
  {
    "brand": "Slotex",
    "name": "2340_bst_gloria_a4",
    "file": "Slotex/2340_bst_gloria_a4.jpg",
    "url": "https://raw.githubusercontent.com/mebelshare/spacemebel-decors/main/Slotex/2340_bst_gloria_a4.jpg"
  },
  {
    "brand": "Slotex",
    "name": "2385_mramor-bezhevyj-svetlyj_600x1300",
    "file": "Slotex/2385_mramor-bezhevyj-svetlyj_600x1300.jpg",
    "url": "https://raw.githubusercontent.com/mebelshare/spacemebel-decors/main/Slotex/2385_mramor-bezhevyj-svetlyj_600x1300.jpg"
  },
  {
    "brand": "Slotex",
    "name": "2431_q_orion_600x1300",
    "file": "Slotex/2431_q_orion_600x1300.jpg",
    "url": "https://raw.githubusercontent.com/mebelshare/spacemebel-decors/main/Slotex/2431_q_orion_600x1300.jpg"
  },
  {
    "brand": "Slotex",
    "name": "2435_s_kvarts-chernyj_600x1300",
    "file": "Slotex/2435_s_kvarts-chernyj_600x1300.jpg",
    "url": "https://raw.githubusercontent.com/mebelshare/spacemebel-decors/main/Slotex/2435_s_kvarts-chernyj_600x1300.jpg"
  },
  {
    "brand": "Slotex",
    "name": "2580_s_travertin-rimskij_600x1300",
    "file": "Slotex/2580_s_travertin-rimskij_600x1300.jpg",
    "url": "https://raw.githubusercontent.com/mebelshare/spacemebel-decors/main/Slotex/2580_s_travertin-rimskij_600x1300.jpg"
  },
  {
    "brand": "Slotex",
    "name": "2612_p_irish-oak_600x1300",
    "file": "Slotex/2612_p_irish-oak_600x1300.jpg",
    "url": "https://raw.githubusercontent.com/mebelshare/spacemebel-decors/main/Slotex/2612_p_irish-oak_600x1300.jpg"
  },
  {
    "brand": "Slotex",
    "name": "2613_dub-shotlandskij-_600x1300",
    "file": "Slotex/2613_dub-shotlandskij-_600x1300.jpg",
    "url": "https://raw.githubusercontent.com/mebelshare/spacemebel-decors/main/Slotex/2613_dub-shotlandskij-_600x1300.jpg"
  },
  {
    "brand": "Slotex",
    "name": "2631_7_marino_600x1300",
    "file": "Slotex/2631_7_marino_600x1300.jpg",
    "url": "https://raw.githubusercontent.com/mebelshare/spacemebel-decors/main/Slotex/2631_7_marino_600x1300.jpg"
  },
  {
    "brand": "Slotex",
    "name": "2647_m_avalon_600x1300",
    "file": "Slotex/2647_m_avalon_600x1300.jpg",
    "url": "https://raw.githubusercontent.com/mebelshare/spacemebel-decors/main/Slotex/2647_m_avalon_600x1300.jpg"
  },
  {
    "brand": "Slotex",
    "name": "2907_s_turetskij-liker_600x1300",
    "file": "Slotex/2907_s_turetskij-liker_600x1300.jpg",
    "url": "https://raw.githubusercontent.com/mebelshare/spacemebel-decors/main/Slotex/2907_s_turetskij-liker_600x1300.jpg"
  },
  {
    "brand": "Slotex",
    "name": "2925_a_mramor-chernyj_600x1300",
    "file": "Slotex/2925_a_mramor-chernyj_600x1300.jpg",
    "url": "https://raw.githubusercontent.com/mebelshare/spacemebel-decors/main/Slotex/2925_a_mramor-chernyj_600x1300.jpg"
  },
  {
    "brand": "Slotex",
    "name": "2926_a_neapol_600x1300",
    "file": "Slotex/2926_a_neapol_600x1300.jpg",
    "url": "https://raw.githubusercontent.com/mebelshare/spacemebel-decors/main/Slotex/2926_a_neapol_600x1300.jpg"
  },
  {
    "brand": "Slotex",
    "name": "2927_q_verona_600x1300",
    "file": "Slotex/2927_q_verona_600x1300.jpg",
    "url": "https://raw.githubusercontent.com/mebelshare/spacemebel-decors/main/Slotex/2927_q_verona_600x1300.jpg"
  },
  {
    "brand": "Slotex",
    "name": "2929_mw_kaza-strajp-belyj_600x1300",
    "file": "Slotex/2929_mw_kaza-strajp-belyj_600x1300.jpg",
    "url": "https://raw.githubusercontent.com/mebelshare/spacemebel-decors/main/Slotex/2929_mw_kaza-strajp-belyj_600x1300.jpg"
  },
  {
    "brand": "Slotex",
    "name": "2946_r_galiya_600x1300",
    "file": "Slotex/2946_r_galiya_600x1300.jpg",
    "url": "https://raw.githubusercontent.com/mebelshare/spacemebel-decors/main/Slotex/2946_r_galiya_600x1300.jpg"
  },
  {
    "brand": "Slotex",
    "name": "3213_p_sevilskaya-oliva-svetlaya_600x1300",
    "file": "Slotex/3213_p_sevilskaya-oliva-svetlaya_600x1300.jpg",
    "url": "https://raw.githubusercontent.com/mebelshare/spacemebel-decors/main/Slotex/3213_p_sevilskaya-oliva-svetlaya_600x1300.jpg"
  },
  {
    "brand": "Slotex",
    "name": "3259_7_dub-frantsuzskij_600x1300",
    "file": "Slotex/3259_7_dub-frantsuzskij_600x1300.jpg",
    "url": "https://raw.githubusercontent.com/mebelshare/spacemebel-decors/main/Slotex/3259_7_dub-frantsuzskij_600x1300.jpg"
  },
  {
    "brand": "Slotex",
    "name": "3497_bst_diamant-belyj_600x1300",
    "file": "Slotex/3497_bst_diamant-belyj_600x1300.jpg",
    "url": "https://raw.githubusercontent.com/mebelshare/spacemebel-decors/main/Slotex/3497_bst_diamant-belyj_600x1300.jpg"
  },
  {
    "brand": "Slotex",
    "name": "3827_7_-dub-burgas_600x1300",
    "file": "Slotex/3827_7_-dub-burgas_600x1300.jpg",
    "url": "https://raw.githubusercontent.com/mebelshare/spacemebel-decors/main/Slotex/3827_7_-dub-burgas_600x1300.jpg"
  },
  {
    "brand": "Slotex",
    "name": "3829_nw_dub-bunratti_600h1300",
    "file": "Slotex/3829_nw_dub-bunratti_600h1300.jpg",
    "url": "https://raw.githubusercontent.com/mebelshare/spacemebel-decors/main/Slotex/3829_nw_dub-bunratti_600h1300.jpg"
  },
  {
    "brand": "Slotex",
    "name": "4901_6_bronza_600x1300",
    "file": "Slotex/4901_6_bronza_600x1300.jpg",
    "url": "https://raw.githubusercontent.com/mebelshare/spacemebel-decors/main/Slotex/4901_6_bronza_600x1300.jpg"
  },
  {
    "brand": "Slotex",
    "name": "5011_sc_garza_a4",
    "file": "Slotex/5011_sc_garza_a4.jpg",
    "url": "https://raw.githubusercontent.com/mebelshare/spacemebel-decors/main/Slotex/5011_sc_garza_a4.jpg"
  },
  {
    "brand": "Slotex",
    "name": "5012_bst_loft_600x1300",
    "file": "Slotex/5012_bst_loft_600x1300.jpg",
    "url": "https://raw.githubusercontent.com/mebelshare/spacemebel-decors/main/Slotex/5012_bst_loft_600x1300.jpg"
  },
  {
    "brand": "Slotex",
    "name": "5014_sc_pepita_600x1300",
    "file": "Slotex/5014_sc_pepita_600x1300.jpg",
    "url": "https://raw.githubusercontent.com/mebelshare/spacemebel-decors/main/Slotex/5014_sc_pepita_600x1300.jpg"
  },
  {
    "brand": "Slotex",
    "name": "5035_q_gray-granite_600x1300",
    "file": "Slotex/5035_q_gray-granite_600x1300.jpg",
    "url": "https://raw.githubusercontent.com/mebelshare/spacemebel-decors/main/Slotex/5035_q_gray-granite_600x1300.jpg"
  },
  {
    "brand": "Slotex",
    "name": "5040_sl_emperador-marble_600x1300",
    "file": "Slotex/5040_sl_emperador-marble_600x1300.jpg",
    "url": "https://raw.githubusercontent.com/mebelshare/spacemebel-decors/main/Slotex/5040_sl_emperador-marble_600x1300.jpg"
  },
  {
    "brand": "Slotex",
    "name": "5045_bst_black-stone_600x600",
    "file": "Slotex/5045_bst_black-stone_600x600.jpg",
    "url": "https://raw.githubusercontent.com/mebelshare/spacemebel-decors/main/Slotex/5045_bst_black-stone_600x600.jpg"
  },
  {
    "brand": "Slotex",
    "name": "5055_a_active_marble",
    "file": "Slotex/5055_a_active_marble.jpg",
    "url": "https://raw.githubusercontent.com/mebelshare/spacemebel-decors/main/Slotex/5055_a_active_marble.jpg"
  },
  {
    "brand": "Slotex",
    "name": "5101_1_ledyanaya-iskra-belaya_600x1300",
    "file": "Slotex/5101_1_ledyanaya-iskra-belaya_600x1300.jpg",
    "url": "https://raw.githubusercontent.com/mebelshare/spacemebel-decors/main/Slotex/5101_1_ledyanaya-iskra-belaya_600x1300.jpg"
  },
  {
    "brand": "Slotex",
    "name": "5108_1_ledyanaya-iskra-svetlaya_600x1300",
    "file": "Slotex/5108_1_ledyanaya-iskra-svetlaya_600x1300.jpg",
    "url": "https://raw.githubusercontent.com/mebelshare/spacemebel-decors/main/Slotex/5108_1_ledyanaya-iskra-svetlaya_600x1300.jpg"
  },
  {
    "brand": "Slotex",
    "name": "5109_1_ledyanaya-iskra-temnaya_600x1300",
    "file": "Slotex/5109_1_ledyanaya-iskra-temnaya_600x1300.jpg",
    "url": "https://raw.githubusercontent.com/mebelshare/spacemebel-decors/main/Slotex/5109_1_ledyanaya-iskra-temnaya_600x1300.jpg"
  },
  {
    "brand": "Slotex",
    "name": "6021_r_granit-pepelnyj_600x1300",
    "file": "Slotex/6021_r_granit-pepelnyj_600x1300.jpg",
    "url": "https://raw.githubusercontent.com/mebelshare/spacemebel-decors/main/Slotex/6021_r_granit-pepelnyj_600x1300.jpg"
  },
  {
    "brand": "Slotex",
    "name": "6028_r_granit-tigrovyj_600x1300",
    "file": "Slotex/6028_r_granit-tigrovyj_600x1300.jpg",
    "url": "https://raw.githubusercontent.com/mebelshare/spacemebel-decors/main/Slotex/6028_r_granit-tigrovyj_600x1300.jpg"
  },
  {
    "brand": "Slotex",
    "name": "6035_sl_mramor-serebristyj_600ch1300",
    "file": "Slotex/6035_sl_mramor-serebristyj_600ch1300.jpg",
    "url": "https://raw.githubusercontent.com/mebelshare/spacemebel-decors/main/Slotex/6035_sl_mramor-serebristyj_600ch1300.jpg"
  },
  {
    "brand": "Slotex",
    "name": "7110_mw_arabika-pesochnaya_600x1300",
    "file": "Slotex/7110_mw_arabika-pesochnaya_600x1300.jpg",
    "url": "https://raw.githubusercontent.com/mebelshare/spacemebel-decors/main/Slotex/7110_mw_arabika-pesochnaya_600x1300.jpg"
  },
  {
    "brand": "Slotex",
    "name": "7120_7_dub-karpenter_600x1300",
    "file": "Slotex/7120_7_dub-karpenter_600x1300.jpg",
    "url": "https://raw.githubusercontent.com/mebelshare/spacemebel-decors/main/Slotex/7120_7_dub-karpenter_600x1300.jpg"
  },
  {
    "brand": "Slotex",
    "name": "7122_dub-karpenter-temnyj_600x1300",
    "file": "Slotex/7122_dub-karpenter-temnyj_600x1300.jpg",
    "url": "https://raw.githubusercontent.com/mebelshare/spacemebel-decors/main/Slotex/7122_dub-karpenter-temnyj_600x1300.jpg"
  },
  {
    "brand": "Slotex",
    "name": "7141_sc_dub-souberi-svetlyj_600x1300",
    "file": "Slotex/7141_sc_dub-souberi-svetlyj_600x1300.jpg",
    "url": "https://raw.githubusercontent.com/mebelshare/spacemebel-decors/main/Slotex/7141_sc_dub-souberi-svetlyj_600x1300.jpg"
  },
  {
    "brand": "Slotex",
    "name": "7142_rw_dub-souberi-temnyj_600h1300",
    "file": "Slotex/7142_rw_dub-souberi-temnyj_600h1300.jpg",
    "url": "https://raw.githubusercontent.com/mebelshare/spacemebel-decors/main/Slotex/7142_rw_dub-souberi-temnyj_600h1300.jpg"
  },
  {
    "brand": "Slotex",
    "name": "7144_rw_dub-souberi-seryj_600x1300",
    "file": "Slotex/7144_rw_dub-souberi-seryj_600x1300.jpg",
    "url": "https://raw.githubusercontent.com/mebelshare/spacemebel-decors/main/Slotex/7144_rw_dub-souberi-seryj_600x1300.jpg"
  },
  {
    "brand": "Slotex",
    "name": "7191_rw_molokaj_600x1300",
    "file": "Slotex/7191_rw_molokaj_600x1300.jpg",
    "url": "https://raw.githubusercontent.com/mebelshare/spacemebel-decors/main/Slotex/7191_rw_molokaj_600x1300.jpg"
  },
  {
    "brand": "Slotex",
    "name": "8011_s_typesetter",
    "file": "Slotex/8011_s_typesetter.jpg",
    "url": "https://raw.githubusercontent.com/mebelshare/spacemebel-decors/main/Slotex/8011_s_typesetter.jpg"
  },
  {
    "brand": "Slotex",
    "name": "8023_s_istanbul",
    "file": "Slotex/8023_s_istanbul.jpg",
    "url": "https://raw.githubusercontent.com/mebelshare/spacemebel-decors/main/Slotex/8023_s_istanbul.jpg"
  },
  {
    "brand": "Slotex",
    "name": "8028_bst_alicante",
    "file": "Slotex/8028_bst_alicante.jpg",
    "url": "https://raw.githubusercontent.com/mebelshare/spacemebel-decors/main/Slotex/8028_bst_alicante.jpg"
  },
  {
    "brand": "Slotex",
    "name": "8029_s_monte-coto",
    "file": "Slotex/8029_s_monte-coto.jpg",
    "url": "https://raw.githubusercontent.com/mebelshare/spacemebel-decors/main/Slotex/8029_s_monte-coto.jpg"
  },
  {
    "brand": "Slotex",
    "name": "8034_s_rhodes",
    "file": "Slotex/8034_s_rhodes.jpg",
    "url": "https://raw.githubusercontent.com/mebelshare/spacemebel-decors/main/Slotex/8034_s_rhodes.jpg"
  },
  {
    "brand": "Slotex",
    "name": "8039_so_valencia",
    "file": "Slotex/8039_so_valencia.jpg",
    "url": "https://raw.githubusercontent.com/mebelshare/spacemebel-decors/main/Slotex/8039_so_valencia.jpg"
  },
  {
    "brand": "Slotex",
    "name": "8040_sl_crystal-marble",
    "file": "Slotex/8040_sl_crystal-marble.jpg",
    "url": "https://raw.githubusercontent.com/mebelshare/spacemebel-decors/main/Slotex/8040_sl_crystal-marble.jpg"
  },
  {
    "brand": "Slotex",
    "name": "8041_bst_limestone",
    "file": "Slotex/8041_bst_limestone.jpg",
    "url": "https://raw.githubusercontent.com/mebelshare/spacemebel-decors/main/Slotex/8041_bst_limestone.jpg"
  },
  {
    "brand": "Slotex",
    "name": "8044_r_hexastone",
    "file": "Slotex/8044_r_hexastone.jpg",
    "url": "https://raw.githubusercontent.com/mebelshare/spacemebel-decors/main/Slotex/8044_r_hexastone.jpg"
  },
  {
    "brand": "Slotex",
    "name": "8045_1_art-deco",
    "file": "Slotex/8045_1_art-deco.jpg",
    "url": "https://raw.githubusercontent.com/mebelshare/spacemebel-decors/main/Slotex/8045_1_art-deco.jpg"
  },
  {
    "brand": "Slotex",
    "name": "8047_sl_creamy-stone",
    "file": "Slotex/8047_sl_creamy-stone.jpg",
    "url": "https://raw.githubusercontent.com/mebelshare/spacemebel-decors/main/Slotex/8047_sl_creamy-stone.jpg"
  },
  {
    "brand": "Slotex",
    "name": "8048_sl_frosty-marble",
    "file": "Slotex/8048_sl_frosty-marble.jpg",
    "url": "https://raw.githubusercontent.com/mebelshare/spacemebel-decors/main/Slotex/8048_sl_frosty-marble.jpg"
  },
  {
    "brand": "Slotex",
    "name": "8050_sl_sandy-marble",
    "file": "Slotex/8050_sl_sandy-marble.jpg",
    "url": "https://raw.githubusercontent.com/mebelshare/spacemebel-decors/main/Slotex/8050_sl_sandy-marble.jpg"
  },
  {
    "brand": "Slotex",
    "name": "8052_sl_italian_marble",
    "file": "Slotex/8052_sl_italian_marble.jpg",
    "url": "https://raw.githubusercontent.com/mebelshare/spacemebel-decors/main/Slotex/8052_sl_italian_marble.jpg"
  },
  {
    "brand": "Slotex",
    "name": "8053_r_mystic-marble",
    "file": "Slotex/8053_r_mystic-marble.jpg",
    "url": "https://raw.githubusercontent.com/mebelshare/spacemebel-decors/main/Slotex/8053_r_mystic-marble.jpg"
  },
  {
    "brand": "Slotex",
    "name": "8054_r_white-onyx",
    "file": "Slotex/8054_r_white-onyx.jpg",
    "url": "https://raw.githubusercontent.com/mebelshare/spacemebel-decors/main/Slotex/8054_r_white-onyx.jpg"
  },
  {
    "brand": "Slotex",
    "name": "8055_sl_brazilian-marble",
    "file": "Slotex/8055_sl_brazilian-marble.jpg",
    "url": "https://raw.githubusercontent.com/mebelshare/spacemebel-decors/main/Slotex/8055_sl_brazilian-marble.jpg"
  },
  {
    "brand": "Slotex",
    "name": "8056_q_desert-stone",
    "file": "Slotex/8056_q_desert-stone.jpg",
    "url": "https://raw.githubusercontent.com/mebelshare/spacemebel-decors/main/Slotex/8056_q_desert-stone.jpg"
  },
  {
    "brand": "Slotex",
    "name": "8060_r_smoky-quartz",
    "file": "Slotex/8060_r_smoky-quartz.jpg",
    "url": "https://raw.githubusercontent.com/mebelshare/spacemebel-decors/main/Slotex/8060_r_smoky-quartz.jpg"
  },
  {
    "brand": "Slotex",
    "name": "8061_r_honey_quartz",
    "file": "Slotex/8061_r_honey_quartz.jpg",
    "url": "https://raw.githubusercontent.com/mebelshare/spacemebel-decors/main/Slotex/8061_r_honey_quartz.jpg"
  },
  {
    "brand": "Slotex",
    "name": "8063_q_volcano",
    "file": "Slotex/8063_q_volcano.jpg",
    "url": "https://raw.githubusercontent.com/mebelshare/spacemebel-decors/main/Slotex/8063_q_volcano.jpg"
  },
  {
    "brand": "Slotex",
    "name": "8070_rw_rustic-wood",
    "file": "Slotex/8070_rw_rustic-wood.jpg",
    "url": "https://raw.githubusercontent.com/mebelshare/spacemebel-decors/main/Slotex/8070_rw_rustic-wood.jpg"
  },
  {
    "brand": "Slotex",
    "name": "8071_rw_gray-rustic-wood",
    "file": "Slotex/8071_rw_gray-rustic-wood.jpg",
    "url": "https://raw.githubusercontent.com/mebelshare/spacemebel-decors/main/Slotex/8071_rw_gray-rustic-wood.jpg"
  },
  {
    "brand": "Slotex",
    "name": "8072_rw_snowy-oak",
    "file": "Slotex/8072_rw_snowy-oak.jpg",
    "url": "https://raw.githubusercontent.com/mebelshare/spacemebel-decors/main/Slotex/8072_rw_snowy-oak.jpg"
  }
]
